flams/__init__.py
flams/display.py
flams/flams.py
flams/input.py
flams/run_blast.py
flams/utils.py
flams/databases/__init__.py
flams/databases/cplmv4.py
flams/databases/dbptm.py
flams/databases/setup.py
flams-1.1.6.dist-info/licenses/LICENSE
flams-1.1.6.dist-info/METADATA
flams-1.1.6.dist-info/WHEEL
flams-1.1.6.dist-info/entry_points.txt
flams-1.1.6.dist-info/top_level.txt
flams-1.1.6.dist-info/RECORD
