Metadata-Version: 2.4
Name: flams
Version: 1.1.6
Summary: Find Lysine Acylations & other Modification Sites
Project-URL: repository, https://github.com/hannelorelongin/FLAMS
Requires-Python: >=3.10
License-File: LICENSE
Requires-Dist: appdirs==1.4.4
Requires-Dist: biopython==1.81
Requires-Dist: certifi==2023.5.7
Requires-Dist: charset-normalizer==3.3.2
Requires-Dist: idna==3.4
Requires-Dist: numpy==1.24.3
Requires-Dist: pandas==2.1.2
Requires-Dist: python-dateutil==2.8.2
Requires-Dist: pytz==2023.3.post1
Requires-Dist: requests==2.29.0
Requires-Dist: six==1.16.0
Requires-Dist: tzdata==2023.3
Requires-Dist: urllib3==1.26.18
Dynamic: license-file
